xwmt/__init__.py
xwmt/compute.py
xwmt/version.py
xwmt/wm.py
xwmt/wmt.py
xwmt/tests/conftest.py
xwmt/tests/test_convergence_to_analytical.py
xwmt/tests/test_integrate_transformations.py
xwmt-0.1.0.dist-info/METADATA
xwmt-0.1.0.dist-info/WHEEL
xwmt-0.1.0.dist-info/licenses/LICENSE
xwmt-0.1.0.dist-info/RECORD
