Metadata-Version: 2.4
Name: xwmt
Version: 0.1.0
Summary: Water Mass Transformation Routines for xarray
Project-URL: Homepage, https://github.com/NOAA-GFDL/xwmt
Project-URL: Bugs/Issues/Features, https://github.com/NOAA-GFDL/xwmt/issues
Project-URL: Related package, https://github.com/hdrake/xwmb
Author-email: Jan-Erik Tesdal <jt7058@princeton.edu>, "Henri F. Drake" <hfdrake@uci.edu>
License-File: LICENSE
Keywords: ocean modeling,oceanography,water mass transformation
Classifier: Development Status :: 3 - Alpha
Classifier: Intended Audience :: Science/Research
Classifier: License :: OSI Approved :: MIT License
Classifier: Operating System :: OS Independent
Classifier: Programming Language :: Python :: 3.8
Classifier: Programming Language :: Python :: 3.9
Classifier: Programming Language :: Python :: 3.10
Classifier: Topic :: Scientific/Engineering
Requires-Python: >=3.8
Requires-Dist: gsw
Requires-Dist: numba
Requires-Dist: numpy
Requires-Dist: pandas
Requires-Dist: xarray
Requires-Dist: xbudget>=0.5.0
Requires-Dist: xgcm>=0.9.0
Requires-Dist: xhistogram
